eli5/__init__.py
eli5/_decision_path.py
eli5/_feature_importances.py
eli5/_feature_names.py
eli5/_feature_weights.py
eli5/_graphviz.py
eli5/base.py
eli5/base_utils.py
eli5/catboost.py
eli5/explain.py
eli5/ipython.py
eli5/lightgbm.py
eli5/lightning.py
eli5/permutation_importance.py
eli5/transform.py
eli5/utils.py
eli5/xgboost.py
eli5/formatters/__init__.py
eli5/formatters/as_dataframe.py
eli5/formatters/as_dict.py
eli5/formatters/features.py
eli5/formatters/fields.py
eli5/formatters/html.py
eli5/formatters/image.py
eli5/formatters/text.py
eli5/formatters/text_helpers.py
eli5/formatters/trees.py
eli5/formatters/utils.py
eli5/keras/__init__.py
eli5/keras/explain_prediction.py
eli5/keras/gradcam.py
eli5/lime/__init__.py
eli5/lime/_vectorizer.py
eli5/lime/lime.py
eli5/lime/samplers.py
eli5/lime/textutils.py
eli5/lime/utils.py
eli5/llm/__init__.py
eli5/llm/explain_prediction.py
eli5/sklearn/__init__.py
eli5/sklearn/_span_analyzers.py
eli5/sklearn/explain_prediction.py
eli5/sklearn/explain_weights.py
eli5/sklearn/permutation_importance.py
eli5/sklearn/text.py
eli5/sklearn/transform.py
eli5/sklearn/treeinspect.py
eli5/sklearn/unhashing.py
eli5/sklearn/utils.py
eli5/sklearn_crfsuite/__init__.py
eli5/sklearn_crfsuite/explain_weights.py
eli5/templates/explain.html
eli5/templates/feature_importances.html
eli5/templates/styles.html
eli5/templates/target_header.html
eli5/templates/transition_features.html
eli5/templates/weighted_spans.html
eli5/templates/weights.html
eli5/templates/weights_table.html
eli5/templates/weights_table_row.html
eli5-0.15.0.dist-info/licenses/LICENSE.txt
eli5-0.15.0.dist-info/METADATA
eli5-0.15.0.dist-info/WHEEL
eli5-0.15.0.dist-info/top_level.txt
eli5-0.15.0.dist-info/RECORD
