Metadata-Version: 2.4
Name: eli5
Version: 0.15.0
Summary: Debug machine learning classifiers and explain their predictions
Home-page: https://github.com/eli5-org/eli5
Author: Mikhail Korobov, Konstantin Lopuhin
Author-email: kmike84@gmail.com, kostia.lopuhin@gmail.com
License: MIT license
Classifier: Development Status :: 4 - Beta
Classifier: License :: OSI Approved :: MIT License
Classifier: Intended Audience :: Developers
Classifier: Operating System :: OS Independent
Classifier: Programming Language :: Python
Classifier: Programming Language :: Python :: 3
Classifier: Programming Language :: Python :: 3.9
Classifier: Programming Language :: Python :: 3.10
Classifier: Programming Language :: Python :: 3.11
Classifier: Programming Language :: Python :: 3.12
Classifier: Programming Language :: Python :: 3.13
Requires-Python: >=3.9
License-File: LICENSE.txt
Requires-Dist: attrs>17.1.0
Requires-Dist: jinja2>=3.0.0
Requires-Dist: numpy>=1.9.0
Requires-Dist: scipy
Requires-Dist: scikit-learn>=1.6.0
Requires-Dist: graphviz
Requires-Dist: tabulate>=0.7.7
Dynamic: author
Dynamic: author-email
Dynamic: classifier
Dynamic: description
Dynamic: home-page
Dynamic: license
Dynamic: license-file
Dynamic: requires-dist
Dynamic: requires-python
Dynamic: summary
